<ClassData>
  <CharacterClass>
    <Name>Junker</Name>
    <SizeType>NORMAL</SizeType>
    <ForwardAction_0>Hit</ForwardAction_0>
    <RearAction_0>Hit</RearAction_0>
    <ActivatedAction_0>Smash</ActivatedAction_0>
    <ActivatedAction_1>Rally</ActivatedAction_1>
    <LeaderBonus>None</LeaderBonus>
    <InnateBonus_0>None</InnateBonus_0>
    <Alignment>0</Alignment>
    <StatOnLevelUpOdds>
      <ATK>3</ATK>
      <DEF>3</DEF>
      <AGI>3</AGI>
      <MAG>2</MAG>
      <SPI>3</SPI>
      <MND>2</MND>
      <CHA>2</CHA>
      <RES>2</RES>
      <SPD>2</SPD>
      <LUK>3</LUK>
    </StatOnLevelUpOdds>
  </CharacterClass>
 
</ClassData>